ipsos_credibility_interval/__init__.py
ipsos_credibility_interval-0.0.3.dist-info/LICENSE
ipsos_credibility_interval-0.0.3.dist-info/METADATA
ipsos_credibility_interval-0.0.3.dist-info/WHEEL
ipsos_credibility_interval-0.0.3.dist-info/top_level.txt
ipsos_credibility_interval-0.0.3.dist-info/RECORD
